django_htmx_messages/__init__.py
django_htmx_messages/apps.py
django_htmx_messages/conf.py
django_htmx_messages/main.py
django_htmx_messages/middleware.py
django_htmx_messages/py.typed
django_htmx_messages/migrations/__init__.py
django_htmx_messages/static/toasts.js
django_htmx_messages/templates/toasts.html
django_htmx_messages-0.1.1.dist-info/LICENSE
django_htmx_messages-0.1.1.dist-info/METADATA
django_htmx_messages-0.1.1.dist-info/WHEEL
django_htmx_messages-0.1.1.dist-info/top_level.txt
django_htmx_messages-0.1.1.dist-info/RECORD
