Metadata-Version: 2.1
Name: django-htmx-messages
Version: 0.1.1
Summary: Django+HTMX integration with the messages framework
Author-email: Abe Hanoka <abe@habet.dev>
License: MIT
Project-URL: Bug Tracker, https://github.com/abe-101/django-htmx-messages/issues
Project-URL: Changelog, https://github.com/abe-101/django-htmx-messages/blob/main/CHANGELOG.md
Project-URL: documentation, https://django-htmx-messages.readthedocs.io
Project-URL: repository, https://github.com/abe-101/django-htmx-messages
Classifier: Development Status :: 2 - Pre-Alpha
Classifier: Intended Audience :: Developers
Classifier: Natural Language :: English
Classifier: Operating System :: OS Independent
Classifier: Framework :: Django
Classifier: Framework :: Django :: 4.2
Classifier: Framework :: Django :: 5.0
Classifier: Framework :: Django :: 5.1
Classifier: Programming Language :: Python :: 3.9
Classifier: Programming Language :: Python :: 3.10
Classifier: Programming Language :: Python :: 3.11
Classifier: Programming Language :: Python :: 3.12
Classifier: Programming Language :: Python :: 3.13
Classifier: Topic :: Software Development :: Libraries
Requires-Python: >=3.9
License-File: LICENSE
Requires-Dist: django>=4.2
